{
    "map": {
        "@_version": "freeplane 1.8.0",
        "node": {
            "@_TEXT": "solid",
            "@_FOLDED": false,
            "@_ID": "ID_237352286",
            "@_CREATED": 1570576809840,
            "@_MODIFIED": 1583701801625,
            "@_ICON_SIZE": "16.0 pt",
            "@_LINK": "../tech/index.mm",
            "@_STYLE": "oval",
            "icon": {
                "@_BUILTIN": "wizard"
            },
            "font": {
                "@_SIZE": 18
            },
            "hook": [
                {
                    "@_NAME": "MapStyle",
                    "properties": {
                        "@_edgeColorConfiguration": "#808080ff,#ff0000ff,#0000ffff,#00ff00ff,#ff00ffff,#00ffffff,#7c0000ff,#00007cff,#007c00ff,#7c007cff,#007c7cff,#7c7c00ff",
                        "@_fit_to_viewport": false
                    },
                    "map_styles": {
                        "stylenode": {
                            "@_LOCALIZED_TEXT": "styles.root_node",
                            "@_STYLE": "oval",
                            "@_UNIFORM_SHAPE": true,
                            "@_VGAP_QUANTITY": "24.0 pt",
                            "font": {
                                "@_SIZE": 24
                            },
                            "stylenode": [
                                {
                                    "@_LOCALIZED_TEXT": "styles.predefined",
                                    "@_POSITION": "right",
                                    "@_STYLE": "bubble",
                                    "stylenode": [
                                        {
                                            "@_LOCALIZED_TEXT": "default",
                                            "@_ICON_SIZE": "12.0 pt",
                                            "@_COLOR": "#000000",
                                            "@_STYLE": "fork",
                                            "font": {
                                                "@_NAME": "SansSerif",
                                                "@_SIZE": 10,
                                                "@_BOLD": false,
                                                "@_ITALIC": false
                                            }
                                        },
                                        {
                                            "@_LOCALIZED_TEXT": "defaultstyle.details"
                                        },
                                        {
                                            "@_LOCALIZED_TEXT": "defaultstyle.attributes",
                                            "font": {
                                                "@_SIZE": 9
                                            }
                                        },
                                        {
                                            "@_LOCALIZED_TEXT": "defaultstyle.note",
                                            "@_COLOR": "#000000",
                                            "@_BACKGROUND_COLOR": "#ffffff",
                                            "@_TEXT_ALIGN": "LEFT"
                                        },
                                        {
                                            "@_LOCALIZED_TEXT": "defaultstyle.floating",
                                            "edge": {
                                                "@_STYLE": "hide_edge"
                                            },
                                            "cloud": {
                                                "@_COLOR": "#f0f0f0",
                                                "@_SHAPE": "ROUND_RECT"
                                            }
                                        }
                                    ]
                                },
                                {
                                    "@_LOCALIZED_TEXT": "styles.user-defined",
                                    "@_POSITION": "right",
                                    "@_STYLE": "bubble",
                                    "stylenode": [
                                        {
                                            "@_LOCALIZED_TEXT": "styles.topic",
                                            "@_COLOR": "#18898b",
                                            "@_STYLE": "fork",
                                            "font": {
                                                "@_NAME": "Liberation Sans",
                                                "@_SIZE": 10,
                                                "@_BOLD": true
                                            }
                                        },
                                        {
                                            "@_LOCALIZED_TEXT": "styles.subtopic",
                                            "@_COLOR": "#cc3300",
                                            "@_STYLE": "fork",
                                            "font": {
                                                "@_NAME": "Liberation Sans",
                                                "@_SIZE": 10,
                                                "@_BOLD": true
                                            }
                                        },
                                        {
                                            "@_LOCALIZED_TEXT": "styles.subsubtopic",
                                            "@_COLOR": "#669900",
                                            "font": {
                                                "@_NAME": "Liberation Sans",
                                                "@_SIZE": 10,
                                                "@_BOLD": true
                                            }
                                        },
                                        {
                                            "@_LOCALIZED_TEXT": "styles.important",
                                            "icon": {
                                                "@_BUILTIN": "yes"
                                            }
                                        }
                                    ]
                                },
                                {
                                    "@_LOCALIZED_TEXT": "styles.AutomaticLayout",
                                    "@_POSITION": "right",
                                    "@_STYLE": "bubble",
                                    "stylenode": [
                                        {
                                            "@_LOCALIZED_TEXT": "AutomaticLayout.level.root",
                                            "@_COLOR": "#000000",
                                            "@_STYLE": "oval",
                                            "@_SHAPE_HORIZONTAL_MARGIN": "10.0 pt",
                                            "@_SHAPE_VERTICAL_MARGIN": "10.0 pt",
                                            "font": {
                                                "@_SIZE": 18
                                            }
                                        },
                                        {
                                            "@_LOCALIZED_TEXT": "AutomaticLayout.level,1",
                                            "@_COLOR": "#0033ff",
                                            "font": {
                                                "@_SIZE": 16
                                            }
                                        },
                                        {
                                            "@_LOCALIZED_TEXT": "AutomaticLayout.level,2",
                                            "@_COLOR": "#00b439",
                                            "font": {
                                                "@_SIZE": 14
                                            }
                                        },
                                        {
                                            "@_LOCALIZED_TEXT": "AutomaticLayout.level,3",
                                            "@_COLOR": "#990000",
                                            "font": {
                                                "@_SIZE": 12
                                            }
                                        },
                                        {
                                            "@_LOCALIZED_TEXT": "AutomaticLayout.level,4",
                                            "@_COLOR": "#111111",
                                            "font": {
                                                "@_SIZE": 10
                                            }
                                        },
                                        {
                                            "@_LOCALIZED_TEXT": "AutomaticLayout.level,5"
                                        },
                                        {
                                            "@_LOCALIZED_TEXT": "AutomaticLayout.level,6"
                                        },
                                        {
                                            "@_LOCALIZED_TEXT": "AutomaticLayout.level,7"
                                        },
                                        {
                                            "@_LOCALIZED_TEXT": "AutomaticLayout.level,8"
                                        },
                                        {
                                            "@_LOCALIZED_TEXT": "AutomaticLayout.level,9"
                                        },
                                        {
                                            "@_LOCALIZED_TEXT": "AutomaticLayout.level,10"
                                        },
                                        {
                                            "@_LOCALIZED_TEXT": "AutomaticLayout.level,11"
                                        }
                                    ]
                                }
                            ]
                        }
                    }
                },
                {
                    "@_NAME": "AutomaticEdgeColor",
                    "@_COUNTER": 20,
                    "@_RULE": "ON_BRANCH_CREATION"
                }
            ],
            "node": [
                {
                    "@_TEXT": "Apps",
                    "@_POSITION": "right",
                    "@_ID": "ID_1861071781",
                    "@_CREATED": 1578130056712,
                    "@_MODIFIED": 1583701795273,
                    "@_LINK": "apps/index.mm",
                    "@_COLOR": "#000099",
                    "@_HGAP_QUANTITY": "-73.7499973848463 pt",
                    "@_VSHIFT_QUANTITY": "-77.24999769777067 pt",
                    "font": {
                        "@_SIZE": 12,
                        "@_BOLD": true
                    },
                    "edge": {
                        "@_STYLE": "bezier",
                        "@_COLOR": "#00ff00",
                        "@_WIDTH": "thin"
                    },
                    "node": {
                        "@_TEXT": "databrowser",
                        "@_ID": "ID_589909741",
                        "@_CREATED": 1579167473579,
                        "@_MODIFIED": 1579167473584,
                        "@_LINK": "databrowser/index.mm",
                        "edge": {
                            "@_STYLE": "bezier",
                            "@_COLOR": "#00ff00",
                            "@_WIDTH": "thin"
                        }
                    }
                },
                {
                    "@_TEXT": "spec",
                    "@_POSITION": "right",
                    "@_ID": "ID_45632273",
                    "@_CREATED": 1574934349622,
                    "@_MODIFIED": 1584566758410,
                    "@_LINK": "spec/index.mm",
                    "@_HGAP_QUANTITY": "25.999999642372142 pt",
                    "@_VSHIFT_QUANTITY": "14.999999552965178 pt",
                    "icon": {
                        "@_BUILTIN": "list"
                    },
                    "edge": {
                        "@_STYLE": "bezier",
                        "@_COLOR": "#00007c",
                        "@_WIDTH": "thin"
                    },
                    "font": {
                        "@_SIZE": 11,
                        "@_BOLD": true
                    }
                },
                {
                    "@_TEXT": "Tools",
                    "@_POSITION": "right",
                    "@_ID": "ID_1810859973",
                    "@_CREATED": 1572063767900,
                    "@_MODIFIED": 1574934302574,
                    "@_HGAP_QUANTITY": "-72.24999742954977 pt",
                    "@_VSHIFT_QUANTITY": "68.24999796599155 pt",
                    "@_COLOR": "#666600",
                    "icon": {
                        "@_BUILTIN": "executable"
                    },
                    "font": {
                        "@_SIZE": 12,
                        "@_BOLD": true
                    },
                    "edge": {
                        "@_COLOR": "#ff00ff"
                    },
                    "node": [
                        {
                            "@_TEXT": "Data Kitchen",
                            "@_ID": "ID_464490085",
                            "@_CREATED": 1573024190055,
                            "@_MODIFIED": 1573024327376,
                            "@_LINK": "https://github.com/solid/data-kitchen",
                            "node": [
                                {
                                    "@_TEXT": "browser FS Fork",
                                    "@_ID": "ID_1249692100",
                                    "@_CREATED": 1580246811384,
                                    "@_MODIFIED": 1580246818624,
                                    "@_LINK": "https://github.com/jeff-zucker/data-kitchen"
                                },
                                {
                                    "@_TEXT": "browser FS notes",
                                    "@_ID": "ID_159496431",
                                    "@_CREATED": 1580246837298,
                                    "@_MODIFIED": 1580246844069,
                                    "@_LINK": "https://github.com/jeff-zucker/data-kitchen/blob/master/README.jz.md#these-things-currenlty-work-using-the-databrowser-in-file-and-app-spaces"
                                }
                            ]
                        },
                        {
                            "@_TEXT": "BrowserFS",
                            "@_ID": "ID_254470917",
                            "@_CREATED": 1573155072181,
                            "@_MODIFIED": 1573155078101,
                            "@_LINK": "https://github.com/jvilk/BrowserFS",
                            "node": {
                                "@_TEXT": "solid rest",
                                "@_ID": "ID_1269514055",
                                "@_CREATED": 1579817003480,
                                "@_MODIFIED": 1579817386779,
                                "@_LINK": "https://github.com/jeff-zucker/solid-rest/tree/browserFS"
                            }
                        },
                        {
                            "@_TEXT": "Fuse library",
                            "@_ID": "ID_845285837",
                            "@_CREATED": 1577063008573,
                            "@_MODIFIED": 1577082125436,
                            "@_LINK": "https://github.com/fuse-friends/fuse-native"
                        }
                    ]
                },
                {
                    "@_TEXT": "Links",
                    "@_POSITION": "left",
                    "@_ID": "ID_777477932",
                    "@_CREATED": 1572063875737,
                    "@_MODIFIED": 1583701801612,
                    "@_COLOR": "#660000",
                    "@_HGAP_QUANTITY": "15.499999955296516 pt",
                    "@_VSHIFT_QUANTITY": "-9.749999709427364 pt",
                    "icon": {
                        "@_BUILTIN": "attach"
                    },
                    "font": {
                        "@_SIZE": 12,
                        "@_BOLD": true
                    },
                    "edge": {
                        "@_COLOR": "#00ffff"
                    },
                    "node": [
                        {
                            "@_ID": "ID_1974475433",
                            "@_CREATED": 1578928125418,
                            "@_MODIFIED": 1578930262924,
                            "@_LINK": "https://webmaps.io/",
                            "@_COLOR": "#000099",
                            "richcontent": {
                                "@_TYPE": "NODE",
                                "html": {
                                    "head": "",
                                    "body": {
                                        "#text": "Made with&#160;using webmaps.io",
                                        "img": {
                                            "@_class": "emoji",
                                            "@_alt": "heart",
                                            "@_height": 20,
                                            "@_width": 20,
                                            "@_src": "https://github.githubassets.com/images/icons/emoji/unicode/2764.png",
                                            "@_style": "border-top-style: none; border-right-style: none; border-bottom-style: none; border-left-style: none"
                                        }
                                    }
                                }
                            },
                            "font": {
                                "@_SIZE": 10,
                                "@_BOLD": true
                            }
                        },
                        {
                            "@_TEXT": "MIT",
                            "@_ID": "ID_671925292",
                            "@_CREATED": 1573024179269,
                            "@_MODIFIED": 1573024358704,
                            "@_LINK": "https://solid.mit.edu"
                        },
                        {
                            "@_TEXT": "issues",
                            "@_ID": "ID_1662681886",
                            "@_CREATED": 1577601478570,
                            "@_MODIFIED": 1577601478579,
                            "@_LINK": "issues/index.mm",
                            "edge": {
                                "@_STYLE": "bezier",
                                "@_COLOR": "#00ffff",
                                "@_WIDTH": "thin"
                            }
                        },
                        {
                            "@_TEXT": "history",
                            "@_ID": "ID_1693475953",
                            "@_CREATED": 1579694166408,
                            "@_MODIFIED": 1579694170918,
                            "@_LINK": "https://www.w3.org/wiki/Socialwg/2015-03-18-minutes"
                        },
                        {
                            "@_TEXT": "solid.community",
                            "@_ID": "ID_246084453",
                            "@_CREATED": 1583701829774,
                            "@_MODIFIED": 1583701829786,
                            "@_LINK": "solid.community/index.mm",
                            "edge": {
                                "@_STYLE": "bezier",
                                "@_COLOR": "#00ffff",
                                "@_WIDTH": "thin"
                            }
                        },
                        {
                            "@_TEXT": "Colors",
                            "@_ID": "ID_960031878",
                            "@_CREATED": 1577179087843,
                            "@_MODIFIED": 1577179091178,
                            "@_LINK": "https://design.inrupt.com/atomic-core/?cat=Core#Colors",
                            "node": {
                                "@_TEXT": "#7C4DFF",
                                "@_ID": "ID_1864362129",
                                "@_CREATED": 1577177083068,
                                "@_MODIFIED": 1577177083068,
                                "node": {
                                    "@_TEXT": "royal lavendar",
                                    "@_ID": "ID_1993946970",
                                    "@_CREATED": 1577177086745,
                                    "@_MODIFIED": 1577177090171
                                }
                            }
                        }
                    ]
                }
            ]
        }
    }
}
